release_test/__init__.py
release_test/main.py
release_test-0.0.1.dist-info/LICENSE
release_test-0.0.1.dist-info/METADATA
release_test-0.0.1.dist-info/WHEEL
release_test-0.0.1.dist-info/top_level.txt
release_test-0.0.1.dist-info/RECORD
