Metadata-Version: 2.1
Name: release-test
Version: 0.0.1
Summary: Download Douyin video without watermark
Home-page: https://github.com/spartanfuk/dyvideo
Author: SpartanFuk
Author-email: 2383731235@qq.com
License: UNKNOWN
Platform: UNKNOWN
Classifier: Programming Language :: Python :: 3
Classifier: License :: OSI Approved :: MIT License
Classifier: Operating System :: OS Independent
Requires-Python: >=3.6
Requires-Dist: requests
